statichl/__init__.py
statichl/__main__.py
statichl/constants.py
statichl/elementutil.py
statichl/pageutil.py
staticHL-0.2.0.dist-info/METADATA
staticHL-0.2.0.dist-info/WHEEL
staticHL-0.2.0.dist-info/entry_points.txt
staticHL-0.2.0.dist-info/top_level.txt
staticHL-0.2.0.dist-info/RECORD
